README.md
data/laMapping.csv
ukcensusapi/NISRA.py
ukcensusapi/NRScotland.py
ukcensusapi/Nomisweb.py
ukcensusapi/NomiswebApi.py
ukcensusapi/Query.py
ukcensusapi/__init__.py
ukcensusapi/utils.py
ukcensusapi-1.1.5.dist-info/METADATA
ukcensusapi-1.1.5.dist-info/RECORD
ukcensusapi-1.1.5.dist-info/WHEEL
ukcensusapi-1.1.5.dist-info/top_level.txt
