Metadata-Version: 2.1
Name: ukcensusapi
Version: 1.1.5
Summary: UK census data query automation
Home-page: https://github.com/virgesmith/UKCensusAPI
Author: Andrew P Smith
Author-email: a.p.smith@leeds.ac.uk
License: UNKNOWN
Platform: UNKNOWN
Classifier: Programming Language :: Python :: 3
Classifier: License :: OSI Approved :: MIT License
Classifier: Operating System :: OS Independent
Requires-Dist: numpy
Requires-Dist: pandas
Requires-Dist: requests
